functions.py
graficas-1.0.dist-info/METADATA
graficas-1.0.dist-info/WHEEL
graficas-1.0.dist-info/top_level.txt
graficas-1.0.dist-info/RECORD
