Metadata-Version: 2.1
Name: graficas
Version: 1.0
Summary: se mostraran tres graficas diferentes 
Author: itzel franco
Requires-Dist: matplotlib
